Minecpp/AST.py
Minecpp/AST_tree_sitter.py
Minecpp/app.py
Minecpp/bug_type_gen.py
Minecpp/checkout.py
Minecpp/diff.py
Minecpp/extract_lines.py
Minecpp/getCommits.py
Minecpp/gitOps.py
Minecpp/main.py
Minecpp/sim.py
Minecpp/szz.py
Minecpp/testCase.py
Minecpp/utils.py
Minecpp/build/my-languages.so
Minecpp/templates/exit.html
Minecpp/templates/index.html
Minecpp/templates/quantitative.html
Minecpp/templates/visualization.html
Minecpp-0.6.dist-info/LICENSE
Minecpp-0.6.dist-info/METADATA
Minecpp-0.6.dist-info/WHEEL
Minecpp-0.6.dist-info/entry_points.txt
Minecpp-0.6.dist-info/top_level.txt
Minecpp-0.6.dist-info/RECORD
