Metadata-Version: 2.1
Name: Minecpp
Version: 0.6
Summary: A tool to mine a GitHub repository and obtain a dataset containing a list of bug-fix pairs and related information.
Author-email: Sai Krishna Avula <avulasaikrishna@iitgn.ac.in>, Shouvick Mondal <shouvick.mondal@iitgn.ac.in>
License: Apache License
Project-URL: Homepage, https://github.com/SET-IITGN/MineCPP
Project-URL: Repository, https://github.com/SET-IITGN/MineCPP.git
Requires-Python: <3.11,>=3.8
License-File: LICENSE
Requires-Dist: chardet (==4.0.0)
Requires-Dist: code-bert-score (==0.4.1)
Requires-Dist: crystalbleu (==0.1)
Requires-Dist: lizard (==1.17.10)
Requires-Dist: nltk (==3.9)
Requires-Dist: numpy (==1.26.4)
Requires-Dist: pandas (==2.0.3)
Requires-Dist: PyDriller (==2.6)
Requires-Dist: torch (==2.1.2)
Requires-Dist: transformers (==4.36.0)
Requires-Dist: tree-sitter (==0.20.4)
Requires-Dist: tqdm
Requires-Dist: flask
Requires-Dist: matplotlib
